torchserve_dashboard/__init__.py
torchserve_dashboard/api.py
torchserve_dashboard/cli.py
torchserve_dashboard/dash.py
torchserve_dashboard/default.torchserve.properties
torchserve_dashboard/setup_tools.py
torchserve_dashboard-0.6.0.dist-info/LICENSE
torchserve_dashboard-0.6.0.dist-info/METADATA
torchserve_dashboard-0.6.0.dist-info/WHEEL
torchserve_dashboard-0.6.0.dist-info/entry_points.txt
torchserve_dashboard-0.6.0.dist-info/top_level.txt
torchserve_dashboard-0.6.0.dist-info/RECORD
