Metadata-Version: 2.1
Name: torchserve-dashboard
Version: 0.6.0
Summary: Torchserve dashboard using Streamlit
Home-page: https://github.com/cceyda
Author: Ceyda Cinarel
Author-email: 15624271+cceyda@users.noreply.github.com
License: Apache Software License
Download-URL: https://github.com/cceyda/torchserve-dashboard
Project-URL: Bug Tracker, https://github.com/cceyda/torchserve-dashboard/issues
Project-URL: Source Code, https://github.com/cceyda/torchserve-dashboard
Keywords: machine learning,torchserve,dashboard,torchserve management,model inference
Platform: any
Classifier: Natural Language :: English
Classifier: Development Status :: 4 - Beta
Classifier: Intended Audience :: Developers
Classifier: License :: OSI Approved :: Apache Software License
Classifier: Operating System :: OS Independent
Classifier: Programming Language :: Python :: 3
Requires-Python: >=3.7
License-File: LICENSE
Requires-Dist: streamlit (==1.11.1)
Provides-Extra: all
Provides-Extra: dev
Provides-Extra: docs
Provides-Extra: extra
Provides-Extra: test
